directdb/__init__.py
directdb/exceptions.py
directdb/postgresql.py
directdb/sqlite.py
directdb-1.2.3.dist-info/LICENSE
directdb-1.2.3.dist-info/METADATA
directdb-1.2.3.dist-info/WHEEL
directdb-1.2.3.dist-info/top_level.txt
directdb-1.2.3.dist-info/RECORD
