Metadata-Version: 2.1
Name: directdb
Version: 1.2.3
Summary: An async package that makes database handling extremely easy!
Author: Cannonball Chris
Author-email: cannonballchris8@gmail.com
Keywords: db,bot,discord bot,database,postgresql,asyncpg,async,pgutils,nosql,sqlite,aiosqlite,discord.py
Classifier: Development Status :: 5 - Production/Stable
Classifier: Intended Audience :: Developers
Classifier: Programming Language :: Python :: 3
Classifier: Operating System :: Unix
Classifier: Operating System :: MacOS :: MacOS X
Classifier: Operating System :: Microsoft :: Windows
License-File: LICENSE
Requires-Dist: asyncpg
Requires-Dist: aiosqlite
